oarepo_upload_cli/__init__.py
oarepo_upload_cli/audit.py
oarepo_upload_cli/config.py
oarepo_upload_cli/entry_points_loader.py
oarepo_upload_cli/exceptions.py
oarepo_upload_cli/main.py
oarepo_upload_cli/null_repository.py
oarepo_upload_cli/repository.py
oarepo_upload_cli/source.py
oarepo_upload_cli/uploader.py
oarepo_upload_cli/utils.py
oarepo_upload_cli/auth/__init__.py
oarepo_upload_cli/auth/bearer_auth.py
oarepo_upload_cli/auth/token_auth.py
oarepo_upload_cli/invenio/__init__.py
oarepo_upload_cli/invenio/client.py
oarepo_upload_cli/invenio/connection.py
oarepo_upload_cli/invenio/record.py
oarepo_upload_cli-1.2.4.dist-info/METADATA
oarepo_upload_cli-1.2.4.dist-info/WHEEL
oarepo_upload_cli-1.2.4.dist-info/entry_points.txt
oarepo_upload_cli-1.2.4.dist-info/top_level.txt
oarepo_upload_cli-1.2.4.dist-info/RECORD
