Metadata-Version: 2.1
Name: oarepo-upload-cli
Version: 1.2.4
Requires-Dist: arrow
Requires-Dist: click
Requires-Dist: python-dotenv
Requires-Dist: requests
Requires-Dist: tqdm
Requires-Dist: importlib-metadata
Provides-Extra: tests
Requires-Dist: pytest ; extra == 'tests'
Requires-Dist: black ; extra == 'tests'
Requires-Dist: isort ; extra == 'tests'
Requires-Dist: autoflake ; extra == 'tests'
